{
    "examId": "x3f34",
    "professor": "Visar Shehu",
    "date": "16/09/2023",
    "marks": 30,
    "time": 120,
    "note": "Please do not feed Tim",
    "triesAllowed": 5,
    "questionsNotes": [
        {
            "Q": "Write a good program",
            "N": "Don't do the thing.",
            "M": 6
        },
        {
            "Q": "Write a good program",
            "N": "Don't do the thing.",
            "M": 6
        },
        {
            "Q": "Write a good program",
            "N": "Don't do the thing.",
            "M": 6
        },
        {
            "Q": "Write a good program",
            "N": "Don't do the thing.",
            "M": 6
        },
        {
            "Q": "Write a good program",
            "N": "Don't do the thing.",
            "M": 6
        }
    ],
    "students": [
        "mk30580",
        "st30578",
        "ri30050"
    ]
}